{
  "project_info": {
    "project_number": "852142063391",
    "project_id": "smart-task-manager-5a73a",
    "storage_bucket": "smart-task-manager-5a73a.firebasestorage.app"
  },
  "client": [
    {
      "client_info": {
        "mobilesdk_app_id": "1:852142063391:android:d9a0fb39e1d58134947a2a",
        "android_client_info": {
          "package_name": "com.example.smart_task_manager"
        }
      },
      "oauth_client": [],
      "api_key": [
        {
          "current_key": "AIzaSyA7KMN-PCIBq0TaMtVlHC7s8K2fO68BqWA"
        }
      ],
      "services": {
        "appinvite_service": {
          "other_platform_oauth_client": []
        }
      }
    }
  ],
  "configuration_version": "1"
}